{"web":{"client_id":"409690530873-qtbgfti5stb0oahs7btcr7n6l1hkft55.apps.googleusercontent.com","project_id":"serene-champion-368806","auth_uri":"https://accounts.google.com/o/oauth2/auth","token_uri":"https://oauth2.googleapis.com/token","auth_provider_x509_cert_url":"https://www.googleapis.com/oauth2/v1/certs","client_secret":"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","redirect_uris":["http://localhost:4001","http://localhost:4001/graphql"],"javascript_origins":["http://localhost","http://localhost:3000"]}}